micropython_mlx90393/__init__.py
micropython_mlx90393/mlx90393.py
micropython_mlx90393-0.1.2.dist-info/LICENSE
micropython_mlx90393-0.1.2.dist-info/METADATA
micropython_mlx90393-0.1.2.dist-info/WHEEL
micropython_mlx90393-0.1.2.dist-info/top_level.txt
micropython_mlx90393-0.1.2.dist-info/RECORD
