Metadata-Version: 2.1
Name: micropython-mlx90393
Version: 0.1.2
Summary: MicroPython Driver for the MLX90393 Sensor
Author-email: "Jose D. Montoya" <mlx90393@mailmeto.mozmail.com>
License: MIT
Project-URL: Homepage, https://github.com/jposada202020/MicroPython_MLX90393
Keywords: micropython,micropython_mlx90393,MicroPython,Sensor,Magnetic,magnetometer
Classifier: Intended Audience :: Developers
Classifier: Topic :: Software Development :: Libraries
Classifier: Topic :: Software Development :: Embedded Systems
Classifier: Topic :: System :: Hardware
Classifier: License :: OSI Approved :: MIT License
Classifier: Programming Language :: Python :: Implementation :: MicroPython
License-File: LICENSE
Provides-Extra: optional
